com_vitalai_haley_taxonomy_domain/__init__.py
com_vitalai_haley_taxonomy_domain/domain-ontology/haley-taxonomy-0.1.0.owl
com_vitalai_haley_taxonomy_domain/model/DomainOntology.py
com_vitalai_haley_taxonomy_domain/model/Edge_hasBroaderCategory.py
com_vitalai_haley_taxonomy_domain/model/Edge_hasBroaderCategory.pyi
com_vitalai_haley_taxonomy_domain/model/Edge_hasEquivalentCategory.py
com_vitalai_haley_taxonomy_domain/model/Edge_hasEquivalentCategory.pyi
com_vitalai_haley_taxonomy_domain/model/Edge_hasNarrowerCategory.py
com_vitalai_haley_taxonomy_domain/model/Edge_hasNarrowerCategory.pyi
com_vitalai_haley_taxonomy_domain/model/Edge_hasRelatedCategory.py
com_vitalai_haley_taxonomy_domain/model/Edge_hasRelatedCategory.pyi
com_vitalai_haley_taxonomy_domain/model/TaxonomyNode.py
com_vitalai_haley_taxonomy_domain/model/TaxonomyNode.pyi
com_vitalai_haley_taxonomy_domain/model/__init__.py
com_vitalai_haley_taxonomy_domain/model/properties/Property_hasDescription.py
com_vitalai_haley_taxonomy_domain/model/properties/Property_hasExternalID.py
com_vitalai_haley_taxonomy_domain/model/properties/Property_isLeafCategory.py
com_vitalai_haley_taxonomy_domain/model/properties/Property_isRootCategory.py
com_vitalai_haley_taxonomy_domain/model/properties/Property_isSelectable.py
com_vitalai_haley_taxonomy_domain/model/properties/__init__.py
vital_ai_haley_taxonomy-0.1.6.dist-info/METADATA
vital_ai_haley_taxonomy-0.1.6.dist-info/WHEEL
vital_ai_haley_taxonomy-0.1.6.dist-info/entry_points.txt
vital_ai_haley_taxonomy-0.1.6.dist-info/top_level.txt
vital_ai_haley_taxonomy-0.1.6.dist-info/RECORD
